polymat/__init__.py
polymat/abc.py
polymat/py.typed
polymat/typing.py
polymat/arrayrepr/__init__.py
polymat/arrayrepr/arrayrepr.py
polymat/arrayrepr/init.py
polymat/expression/__init__.py
polymat/expression/expression.py
polymat/expression/from_.py
polymat/expression/from_.pyi
polymat/expression/init.py
polymat/expression/to.py
polymat/expression/typedexpressions.py
polymat/expression/typedexpressions.pyi
polymat/expressiontree/__init__.py
polymat/expressiontree/from_.py
polymat/expressiontree/init.py
polymat/expressiontree/nodes.py
polymat/expressiontree/to.py
polymat/expressiontree/operations/__init__.py
polymat/expressiontree/operations/addition.py
polymat/expressiontree/operations/assertshape.py
polymat/expressiontree/operations/blockdiagonal.py
polymat/expressiontree/operations/cache.py
polymat/expressiontree/operations/coefficientvector.py
polymat/expressiontree/operations/combinations.py
polymat/expressiontree/operations/definevariable.py
polymat/expressiontree/operations/diagonal.py
polymat/expressiontree/operations/differentiate.py
polymat/expressiontree/operations/elementwisemult.py
polymat/expressiontree/operations/elementwiseopmixin.py
polymat/expressiontree/operations/evaluate.py
polymat/expressiontree/operations/filtermixin.py
polymat/expressiontree/operations/filternonzero.py
polymat/expressiontree/operations/filterpredicator.py
polymat/expressiontree/operations/getitem.py
polymat/expressiontree/operations/kronecker.py
polymat/expressiontree/operations/matrixmultiplication.py
polymat/expressiontree/operations/monomialvector.py
polymat/expressiontree/operations/product.py
polymat/expressiontree/operations/quadraticcoefficients.py
polymat/expressiontree/operations/quadraticmonomials.py
polymat/expressiontree/operations/repeatmatrix.py
polymat/expressiontree/operations/reshape.py
polymat/expressiontree/operations/rowsummation.py
polymat/expressiontree/operations/tosymmetricmatrix.py
polymat/expressiontree/operations/tovariablevector.py
polymat-0.0.8.dist-info/METADATA
polymat-0.0.8.dist-info/WHEEL
polymat-0.0.8.dist-info/licenses/LICENSE
polymat-0.0.8.dist-info/RECORD
