Metadata-Version: 2.4
Name: polymat
Version: 0.0.8
Summary: A library to represent and manipulate multivariate polynomials
Project-URL: Homepage, https://github.com/MichaelSchneeberger/polymat
Author-email: Michael Schneeberger <michael.schneeb@hotmail.com>
License-File: LICENSE
Requires-Dist: dataclassabc>=0.0.10
Requires-Dist: numpy>=2.1.0
Requires-Dist: scipy>=1.14.0
Requires-Dist: statemonad>=0.0.5
Requires-Dist: sympy>=1.13.0
